setup.cfg
setup.py
offshoot/__init__.py
offshoot/base.py
offshoot/main.py
offshoot/manifest.py
offshoot/pluggable.py
offshoot/plugin.py
offshoot.egg-info/PKG-INFO
offshoot.egg-info/SOURCES.txt
offshoot.egg-info/dependency_links.txt
offshoot.egg-info/entry_points.txt
offshoot.egg-info/not-zip-safe
offshoot.egg-info/requires.txt
offshoot.egg-info/top_level.txt