Metadata-Version: 1.1
Name: offshoot
Version: 0.1.6
Summary: Modern, elegant, minimalistic but powerful plugin system for Python 3.5+.
Home-page: https://github.com/SerpentAI/offshoot
Author: Nicholas Brochu
Author-email: nicholas@serpent.ai
License: Apache License v2
Platform: UNKNOWN
Classifier: Development Status :: 5 - Production/Stable
Classifier: Intended Audience :: Developers
Classifier: Natural Language :: English
Classifier: License :: OSI Approved :: Apache Software License
Classifier: Operating System :: OS Independent
Classifier: Programming Language :: Python
Classifier: Programming Language :: Python :: 3.5
Classifier: Programming Language :: Python :: 3.6
